qfc/__init__.py
qfc/codecs/QFCCodec.py
qfc/codecs/QTCCodec.py
qfc/codecs/QWCCodec.py
qfc/codecs/__init__.py
qfc/internal/qfc_compress.py
qfc/internal/qfc_multi_segment_compress.py
qfc/internal/qtc_compress.py
qfc/internal/qwc_compress.py
qfc/internal/qwc_multi_segment_compress.py
qfc-0.3.6.dist-info/METADATA
qfc-0.3.6.dist-info/WHEEL
qfc-0.3.6.dist-info/RECORD
