Metadata-Version: 2.1
Name: qfc
Version: 0.3.6
Summary: 
Author: Jeremy Magland
Author-email: jmagland@flatironinstitute.org
Requires-Python: >=3.8,<4.0
Classifier: Programming Language :: Python :: 3
Classifier: Programming Language :: Python :: 3.8
Classifier: Programming Language :: Python :: 3.9
Classifier: Programming Language :: Python :: 3.10
Classifier: Programming Language :: Python :: 3.11
Classifier: Programming Language :: Python :: 3.12
Requires-Dist: numcodecs (>=0.12.1,<0.13.0)
Requires-Dist: zstandard (>=0.22.0,<0.23.0)
